{"cameraMode":{"drawMode":0,"name":"Shaded","section":"Shading Mode"},"sceneLighting":true,"audioPlay":false,"sceneViewState":{"showFog":true,"showMaterialUpdate":false,"showSkybox":true,"showFlares":true,"showImageEffects":true,"showParticleSystems":true},"in2DMode":false,"pivot":{"x":0.9402192234992981,"y":0.383345365524292,"z":0.32889461517333987},"rotation":{"x":0.0033820392563939096,"y":-0.9953851103782654,"z":-0.08801190555095673,"w":-0.0382349006831646},"size":0.834051787853241,"orthographic":false}